README.md
setup.py
pyreplit/__init__.py
pyreplit/api_pb2.py
pyreplit/main.py
pyreplit.egg-info/PKG-INFO
pyreplit.egg-info/SOURCES.txt
pyreplit.egg-info/dependency_links.txt
pyreplit.egg-info/not-zip-safe
pyreplit.egg-info/requires.txt
pyreplit.egg-info/top_level.txt