Metadata-Version: 2.1
Name: pyreplit
Version: 0.2.3
Summary: Fork of sugarfi/pyrepl
Home-page: https://github.com/AgeOfMarcus/pyreplit
Author: AgeOfMarcus
Author-email: marcus@marcusweinberger.com
License: UNKNOWN
Platform: UNKNOWN
